[
  { "id": "PER", "name": "Perth", "lat": -31.9505, "lng": 115.8605, "type": "cls", "country": "AU" },
  { "id": "SYD", "name": "Sydney", "lat": -33.8688, "lng": 151.2093, "type": "cls", "country": "AU" },
  { "id": "MEL", "name": "Melbourne", "lat": -37.8136, "lng": 144.9631, "type": "cls", "country": "AU" },
  { "id": "BRI", "name": "Brisbane", "lat": -27.4698, "lng": 153.0251, "type": "cls", "country": "AU" },
  { "id": "DAR", "name": "Darwin", "lat": -12.4634, "lng": 130.8456, "type": "cls", "country": "AU" },
  { "id": "AKL", "name": "Auckland", "lat": -36.8509, "lng": 174.7645, "type": "cls", "country": "NZ" },
  { "id": "SIN", "name": "Singapore", "lat": 1.3521, "lng": 103.8198, "type": "cls", "country": "SG" },
  { "id": "HKG", "name": "Hong Kong", "lat": 22.3193, "lng": 114.1694, "type": "cls", "country": "HK" },
  { "id": "TYO", "name": "Tokyo", "lat": 35.6762, "lng": 139.6503, "type": "cls", "country": "JP" },
  { "id": "OSA", "name": "Osaka", "lat": 34.6937, "lng": 135.5023, "type": "cls", "country": "JP" },
  { "id": "GUM", "name": "Guam", "lat": 13.4443, "lng": 144.7937, "type": "cls", "country": "GU" },
  { "id": "HAW", "name": "Hawaii", "lat": 21.3069, "lng": -157.8583, "type": "cls", "country": "US" },
  { "id": "LAX", "name": "Los Angeles", "lat": 34.0522, "lng": -118.2437, "type": "cls", "country": "US" },
  { "id": "SEA", "name": "Seattle", "lat": 47.6062, "lng": -122.3321, "type": "cls", "country": "US" },
  { "id": "MNL", "name": "Manila", "lat": 14.5995, "lng": 120.9842, "type": "cls", "country": "PH" },
  { "id": "TPE", "name": "Taipei", "lat": 25.0330, "lng": 121.5654, "type": "cls", "country": "TW" },
  { "id": "ICN", "name": "Seoul", "lat": 37.5665, "lng": 126.9780, "type": "cls", "country": "KR" },
  { "id": "BOM", "name": "Mumbai", "lat": 19.0760, "lng": 72.8777, "type": "cls", "country": "IN" },
  { "id": "MAA", "name": "Chennai", "lat": 13.0827, "lng": 80.2707, "type": "cls", "country": "IN" },
  { "id": "DJI", "name": "Djibouti", "lat": 11.8251, "lng": 42.5903, "type": "cls", "country": "DJ" },
  { "id": "DXB", "name": "Dubai", "lat": 25.2048, "lng": 55.2708, "type": "cls", "country": "AE" },
  { "id": "LON", "name": "London", "lat": 51.5074, "lng": -0.1278, "type": "cls", "country": "GB" },
  { "id": "JAK", "name": "Jakarta", "lat": -6.2088, "lng": 106.8456, "type": "cls", "country": "ID" },

  { "id": "FRA", "name": "Frankfurt", "lat": 50.1109, "lng": 8.6821, "type": "pop", "country": "DE" },
  { "id": "KUL", "name": "Kuala Lumpur", "lat": 3.1390, "lng": 101.6869, "type": "pop", "country": "MY" },

  { "id": "SYD-EQX", "name": "Sydney Equinix SY1 (Mascot)", "lat": -33.9270, "lng": 151.1987, "type": "pop", "country": "AU" },
  { "id": "SYD-NDC", "name": "Sydney NextDC S1 (Macquarie Park)", "lat": -33.7739, "lng": 151.1215, "type": "pop", "country": "AU" },

  { "id": "TYO-POP", "name": "Tokyo Otemachi", "lat": 35.6872, "lng": 139.7640, "type": "pop", "country": "JP" },
  { "id": "SIN-POP", "name": "Singapore Equinix SG1 (Jurong East)", "lat": 1.3300, "lng": 103.7436, "type": "pop", "country": "SG" }
]
